[
  {
    "product_id": "61974746",
    "name": "여아 스티커북 유아 귀여운 틱톡 2개 스티커폰 캐릭터\n도매꾹판매가 13,600원 (2개 이상 구매) 바로가기",
    "price": "13,600원",
    "price_value": 13600,
    "image": "https://cdn1.domeggook.com/upload/item/2025/11/14/176310863901F05AC53D777CDBD5184B/176310863901F05AC53D777CDBD5184B_img_330?hash=215aa0cc2f61c66f2743e3884748c648",
    "seller": "",
    "link": "https://domemedb.domeggook.com/index/item/itemView.php?itemNo=61974746",
    "grade": "",
    "fast_delivery": true
  },
  {
    "product_id": "61974740",
    "name": "남아 컬렉션 아동 스티커팩 2P 스티커북 스티커 캐릭터\n도매꾹판매가 24,100원 (2개 이상 구매) 바로가기",
    "price": "24,100원",
    "price_value": 24100,
    "image": "https://cdn1.domeggook.com/upload/item/2025/11/14/1763108632A31688A9F18F0BD522279E/1763108632A31688A9F18F0BD522279E_img_330?hash=ce98641878304b2b2f045187c09224b7",
    "seller": "",
    "link": "https://domemedb.domeggook.com/index/item/itemView.php?itemNo=61974740",
    "grade": "",
    "fast_delivery": true
  },
  {
    "product_id": "61974264",
    "name": "3P 귀여운 여아 아동 칭찬스티커 캐릭터 스티커북 칭찬판\n도매꾹판매가 26,900원 (5개 이상 구매) 바로가기",
    "price": "26,900원",
    "price_value": 26900,
    "image": "https://cdn1.domeggook.com/upload/item/2025/11/14/1763108422CC369E74554DA37BE43367/1763108422CC369E74554DA37BE43367_img_330?hash=1fc57e17c75ec8472e6b5a851ffad9b2",
    "seller": "",
    "link": "https://domemedb.domeggook.com/index/item/itemView.php?itemNo=61974264",
    "grade": "",
    "fast_delivery": true
  },
  {
    "product_id": "61974262",
    "name": "귀여운 아동 2P 캐릭터 스티커북 칭찬스티커 여아 칭찬판\n도매꾹판매가 26,300원 (5개 이상 구매) 바로가기",
    "price": "26,300원",
    "price_value": 26300,
    "image": "https://cdn1.domeggook.com/upload/item/2025/11/14/17631084159C3043ACB2AA8319E5A1BF/17631084159C3043ACB2AA8319E5A1BF_img_330?hash=af38b0334006d92fb1240b0cf5ff868a",
    "seller": "",
    "link": "https://domemedb.domeggook.com/index/item/itemView.php?itemNo=61974262",
    "grade": "",
    "fast_delivery": true
  },
  {
    "product_id": "61974260",
    "name": "2개 귀여운 틱톡 캐릭터 어린이 스티커북 스티커폰 아동\n도매꾹판매가 13,600원 (5개 이상 구매) 바로가기",
    "price": "13,600원",
    "price_value": 13600,
    "image": "https://cdn1.domeggook.com/upload/item/2025/11/14/1763108409DC17A165B2EC44AD4152F5/1763108409DC17A165B2EC44AD4152F5_img_330?hash=0ab300199b10c2bbec4b9e57ff0cb64a",
    "seller": "",
    "link": "https://domemedb.domeggook.com/index/item/itemView.php?itemNo=61974260",
    "grade": "",
    "fast_delivery": true
  },
  {
    "product_id": "61974257",
    "name": "스티커폰 캐릭터 귀여운 2개 틱톡 스티커북 아동 어린이\n도매꾹판매가 13,600원 (5개 이상 구매) 바로가기",
    "price": "13,600원",
    "price_value": 13600,
    "image": "https://cdn1.domeggook.com/upload/item/2025/11/14/17631084029AFFCA6D3EF7CEA48AAE16/17631084029AFFCA6D3EF7CEA48AAE16_img_330?hash=aa01d45cbd23c154843e71d08ba0ada6",
    "seller": "",
    "link": "https://domemedb.domeggook.com/index/item/itemView.php?itemNo=61974257",
    "grade": "",
    "fast_delivery": true
  },
  {
    "product_id": "61970166",
    "name": "산리오캐릭터즈 시나모롤 팝업 보석 스티커북\n도매꾹판매가 13,010원 (1개 이상 구매) 바로가기",
    "price": "13,010원",
    "price_value": 13010,
    "image": "https://cdn1.domeggook.com/upload/item/2025/11/14/1763106539B1B5358893C479D08C6BFC/1763106539B1B5358893C479D08C6BFC_img_330?hash=4d38edba122abad8e24cc062d5de355b",
    "seller": "",
    "link": "https://domemedb.domeggook.com/index/item/itemView.php?itemNo=61970166",
    "grade": "",
    "fast_delivery": true
  },
  {
    "product_id": "61970165",
    "name": "산리오캐릭터즈 마이멜로디 팝업 보석 스티커북\n도매꾹판매가 13,010원 (1개 이상 구매) 바로가기",
    "price": "13,010원",
    "price_value": 13010,
    "image": "https://cdn1.domeggook.com/upload/item/2025/11/14/1763106538E7D481AC8A700704BF056D/1763106538E7D481AC8A700704BF056D_img_330?hash=4d38edba122abad8e24cc062d5de355b",
    "seller": "",
    "link": "https://domemedb.domeggook.com/index/item/itemView.php?itemNo=61970165",
    "grade": "",
    "fast_delivery": true
  }
]