[
  {
    "product_id": "61964206",
    "name": "휴대용 인두기 KN116\n도매꾹판매가 14,600원 (1개 이상 구매) 바로가기",
    "price": "14,600원",
    "price_value": 14600,
    "image": "https://cdn1.domeggook.com/upload/item/2025/11/14/17631001236D8A769516182E8C03C222/17631001236D8A769516182E8C03C222_img_330?hash=d1d4c0582f65213de110751adae2ab42",
    "seller": "",
    "link": "https://domemedb.domeggook.com/index/item/itemView.php?itemNo=61964206",
    "grade": "2",
    "fast_delivery": true
  },
  {
    "product_id": "61791295",
    "name": "BURNLEY 1+1 (노란통 솔더링 페이스트57g) 납땜용제\n도매꾹판매가 19,600원 (1개 이상 구매) 바로가기",
    "price": "19,600원",
    "price_value": 19600,
    "image": "https://cdn1.domeggook.com/upload/item/2025/11/05/1762301780B110FFB6D7DD5250ACF408/1762301780B110FFB6D7DD5250ACF408_img_330?hash=89b12798145f05705ccc0afe85546f8c",
    "seller": "",
    "link": "https://domemedb.domeggook.com/index/item/itemView.php?itemNo=61791295",
    "grade": "3",
    "fast_delivery": true
  },
  {
    "product_id": "61775561",
    "name": "BURNLEY 1+1 (노란통 솔더링 페이스트57g) 납땜용제\n도매꾹판매가 18,600원 (1개 이상 구매) 바로가기",
    "price": "18,600원",
    "price_value": 18600,
    "image": "https://cdn1.domeggook.com/upload/item/2025/11/04/176222076506B5BE2FDBD771B7DC5D50/176222076506B5BE2FDBD771B7DC5D50_img_330?hash=8a15c0401210ca2a01180541eb2bfa88",
    "seller": "",
    "link": "https://domemedb.domeggook.com/index/item/itemView.php?itemNo=61775561",
    "grade": "3",
    "fast_delivery": true
  },
  {
    "product_id": "61244875",
    "name": "1+1 BURNLEY (노란통 솔더링 페이스트57g) 납땜용제\n도매꾹판매가 18,600원 (1개 이상 구매) 바로가기",
    "price": "18,600원",
    "price_value": 18600,
    "image": "https://cdn1.domeggook.com/upload/item/2025/10/05/17596300835B719A1A4DEBD2E9AE992D/17596300835B719A1A4DEBD2E9AE992D_img_330?hash=a4cdce71a6143ff850b958fe08cf334b",
    "seller": "",
    "link": "https://domemedb.domeggook.com/index/item/itemView.php?itemNo=61244875",
    "grade": "5",
    "fast_delivery": true
  },
  {
    "product_id": "60512420",
    "name": "코베아 3 WAY 가스 솔더링 KTS 2402\n도매꾹판매가 50,690원 (1개 이상 구매) 바로가기",
    "price": "50,690원",
    "price_value": 50690,
    "image": "https://cdn1.domeggook.com/upload/item/2025/09/02/17567796554E21C5B792D770A7B5BB1F/17567796554E21C5B792D770A7B5BB1F_img_330?hash=2b343a1001b1a679c1c6e512d304a9d0",
    "seller": "",
    "link": "https://domemedb.domeggook.com/index/item/itemView.php?itemNo=60512420",
    "grade": "2",
    "fast_delivery": true
  },
  {
    "product_id": "60436430",
    "name": "솔더링 페이스트 2개 납땜용제 인두팁 보조제 플럭스\n도매꾹판매가 19,500원 (1개 이상 구매) 바로가기",
    "price": "19,500원",
    "price_value": 19500,
    "image": "https://cdn1.domeggook.com/upload/item/2025/08/28/17563485370B6917A502EF5F2B0EC72B/17563485370B6917A502EF5F2B0EC72B_img_330?hash=0ada175324030a83b07aa370a44b8766",
    "seller": "",
    "link": "https://domemedb.domeggook.com/index/item/itemView.php?itemNo=60436430",
    "grade": "9",
    "fast_delivery": true
  },
  {
    "product_id": "60164833",
    "name": "코베아 가스 솔더링 KTS 2402 원터치 압전자동 점화\n도매꾹판매가 49,550원 (1개 이상 구매) 바로가기",
    "price": "49,550원",
    "price_value": 49550,
    "image": "https://cdn1.domeggook.com/upload/item/2025/08/14/1755138329F03436A53B52A2555C7ECE/1755138329F03436A53B52A2555C7ECE_img_330?hash=a0a164db12ca0312f6af369c1ffa36c6",
    "seller": "",
    "link": "https://domemedb.domeggook.com/index/item/itemView.php?itemNo=60164833",
    "grade": "2",
    "fast_delivery": true
  },
  {
    "product_id": "59619558",
    "name": "3RSYS Socoool RC1900 ARGB 솔더링 (BLACK)\n도매꾹판매가 79,500원 (1개 이상 구매) 바로가기",
    "price": "79,500원",
    "price_value": 79500,
    "image": "https://cdn1.domeggook.com/upload/item/2025/07/05/1751691930E355851B27AA7CFA193388/1751691930E355851B27AA7CFA193388_img_330?hash=73c6fcfc1476d4b8c6f759e34f183e70",
    "seller": "",
    "link": "https://domemedb.domeggook.com/index/item/itemView.php?itemNo=59619558",
    "grade": "1",
    "fast_delivery": true
  },
  {
    "product_id": "59619487",
    "name": "3RSYS Socoool RC1900 ARGB 솔더링 (WHITE)\n도매꾹판매가 82,000원 (1개 이상 구매) 바로가기",
    "price": "82,000원",
    "price_value": 82000,
    "image": "https://cdn1.domeggook.com/upload/item/2025/07/05/175169145921C41E7CE267430F93A9A1/175169145921C41E7CE267430F93A9A1_img_330?hash=5e9de222ce66f354f20b0d3d858ec21c",
    "seller": "",
    "link": "https://domemedb.domeggook.com/index/item/itemView.php?itemNo=59619487",
    "grade": "1",
    "fast_delivery": true
  }
]